{"cameraMode":{"drawMode":0,"name":"Shaded","section":"Shading Mode"},"sceneLighting":true,"audioPlay":false,"sceneViewState":{"m_AlwaysRefresh":false,"showFog":true,"showSkybox":false,"showFlares":true,"showImageEffects":true,"showParticleSystems":true,"showVisualEffectGraphs":true,"m_FxEnabled":true},"in2DMode":false,"pivot":{"x":2.418811559677124,"y":0.18209677934646607,"z":-7.438460826873779},"rotation":{"x":0.03199958801269531,"y":-0.724536657333374,"z":0.03371528163552284,"w":0.6876669526100159},"size":1.2247449159622193,"orthographic":false}